<?xml version="1.0" encoding="UTF-8"?>
<unit>
    <id>fr-10-pherc-327-dip-sources</id>
    <creator>Philodemus || Verhasselt, Gertjan</creator>
    <createdAt>1687878884656</createdAt>
    <title>History of the Eleatic and the Atomistic Schools || Fr. 10 PHerc. 327 || Diplomatic Sources</title>
    <target>fr-10-pherc-327</target>
    <children/>
    <dsl>
        <content>Fr. 10   PHerc. 327, cr. 3, pz. 5 (superpos. in parte inf. med.)</content>
        <language>gs-sources</language>
    </dsl>
</unit>