<?xml version="1.0" encoding="UTF-8"?>
<unit>
    <id>fr-08-pherc-1508-lit-app</id>
    <creator>Philodemus || Avdoulou, Eleni</creator>
    <createdAt>1740595971970</createdAt>
    <title>Index Pythagoreorum || Fr. 8 PHerc. 1508 || Literary Apparatus</title>
    <target>fr-08-pherc-1508</target>
    <children/>
    <dsl>
        <content>Fr. 8   primum edidi        3 (-)|βαιν̣ọν̣[τ- vel (-)|βαιν̣ọν̣ [ vel etiam (-)|βαῖν̣ọν̣ [ e.g. *       4 (-)λαμ]β̣αν̣ον̣[τ- vel -|β̣αν̣ον̣ [ vel etiam -]|β̣αν̣ ον̣[ e.g. *        5 ἰα]τρο̣[ e.g. *
</content>
        <language>gs-literary-apparatus</language>
    </dsl>
</unit>