<?xml version="1.0" encoding="UTF-8"?>
<unit>
    <id>fr-60-pherc-1508-dip-app</id>
    <creator>Philodemus || Avdoulou, Eleni</creator>
    <createdAt>1740595973191</createdAt>
    <title>Index Pythagoreorum || Fr. 60 PHerc. 1508 || Diplomatic Apparatus</title>
    <target>fr-60-pherc-1508</target>
    <children/>
    <dsl>
        <content>1 ]α̣[ vert., sup. vest.        2 ]οε[ (π, γ, τ), sup. arcus, (τ, ζ, ξ), inf. vert., (ν, μ), sup. vest.        3 τ[ sin. inf. vest. et dext. inf. vest.        4 υ[ sin. inf. vest.        5 init. ξ̣[ superpos.    ι[ sin. inf. vest.        6 init. νω superpos., post quod bis suppos. litt. unius    fort. δι̣κω̣ superpos.     med. bis suppos. 2 litt.    ante ε superpos. litt. unius 

</content>
        <language>gs-diplomatic-apparatus</language>
    </dsl>
</unit>