<?xml version="1.0" encoding="UTF-8"?>
<unit>
    <id>col-101-pherc-1020-lit-trad</id>
    <creator>Anonymi || Alessandrelli, Michele et Ranocchia, Graziano</creator>
    <createdAt>1740317295331</createdAt>
    <title>Stoici Scriptoris anonymi || Col. 101 PHerc. 1020 || Literary Translation</title>
    <target>col-101-pherc-1020</target>
    <children/>
    <dsl>
        <content>e di essere capaci di ricevere distintamente la [percezione] allotria; [queste cose], infatti, [non staranno] così, [perché] (egli) non è [capace di avvertirla] né la (c. 2 parole mancanti) che essa [è] sconveniente. Certo, [tale cosa] non sarebbe poi del tutto sconveniente, [malvagia] e insieme [turpe]; e, infatti, ciò che è simile a questo (1 verbo mancante) come, d’altra parte, (lo è) [il fatto che] essere eccessivamente inclini alla supposizione [e] all’opinione sia un errore proprio dello stolto; infatti, [colui che con] un’assunzione, anche se (c. 2 parole mancanti) con l’intento di distruggere (c. 1 linea e 3-4 parole mancanti), ma l’[assunzione] mutevole. (c. 2-3 parole mancanti e 14 linee mancanti)</content>
        <language>gs-literary-translation</language>
    </dsl>
</unit>