<?xml version="1.0" encoding="UTF-8"?>
<unit>
    <id>col-98-pherc-1020-dip-tr</id>
    <creator>Anonymi || Alessandrelli, Michele et Ranocchia, Graziano</creator>
    <createdAt>1740317295249</createdAt>
    <title>Stoici Scriptoris anonymi || Col. 98 PHerc. 1020 || Diplomatic Transcription</title>
    <target>col-98-pherc-1020</target>
    <children/>
    <dsl>
        <content>ετ[₍₎]α̣π̣[]ϲια̣
μ̣ε̣ε̣[]ε̣π̣[]ιμ̣ν̣
ανε̣ξ̣[]φο̣τ̣αεα̣
[]ω̣νμενο[
]ν̣[]νγ[]ν
]ντ̣ω̣[]ν̣ω̣ν̣[
με[₍₎]ο̣[][][]
τ̣α̣[]α̣κ̣α̣τ[]ρ̣ο[]ει̣
τ[]α̣ι̣ω[₍₎]οιϲι
του̣τοη̣γ̣α̣ρ̣ξ̣α
πα̣τ̣α̣τ̣[]π̣ν̣δ̣[₍₎]πι
π̣[]ε̣ιδε̣ου̣τ̣ε̣[]αι̣τ̣ε̣ι
[]νο̣[]μ̣α̣ρ̣
[]αρ
τ̣α̣νε̣ιμ̣[]υχ̣α[₍₎]αρ̣
ν̣ει̣δ[][₍₎]ν̣
α[₍₎]τη̣[₍₎]ν̣ν̣α̣τ
τωνου̣[₍₎]μα̣ει
ο̣υδ̣εδιαμ̣[]α[₍₎]ι
ε̣ξμαρ[]αι̣δ[
οω̣νξ[]ατϲ
θα[]π̣[]τη̣ν̣
οιλ̣ο̣[][]ε̣ιν
δι[₍₎]πα[₍₎
₍₎]ξ̣[
desunt versus fere 12
</content>
        <language>gs-diplomatic-transcription</language>
    </dsl>
</unit>