<?xml version="1.0" encoding="UTF-8"?>
<unit>
    <id>kol-15-pherc-1021-dip-app</id>
    <creator>Philodemus || Fleischer, Kilian J.</creator>
    <createdAt>1691590242328</createdAt>
    <title>Academicorum Index || Kol. 15 PHerc. 1021 || Diplomatic Apparatus</title>
    <target>kol-15-pherc-1021</target>
    <children/>
    <dsl>
        <content>

1 οπ ON: Rund., Ti. oben und zwei Vert. unten P || Rund. oben (ρ wahrs.) || Rund. (θ wahrs.) || Rund. || Ti. unten (Schräge) und dann Ti. oben (ob. Teil von  Buchst.) und Ti. mittig (α wahrs.) || Ti. mittig (Verbi. von zwei Buchst.?) || Ti. unten || Ti. unten      2 Ti. unten || Ti. mittig und dann Fall. (υ,ν möglich)       3 α O: Schräge unten P || ρ O || κ O: Ti. oben P      4 φ Ο: Ti. unten und dann oben P      5 ε O || ι O || Ti. mittig       6 Fuß unten       7 Ti. oben       8 ο O: Ti. oben P      9 υ̣ O || π oder τ O: Ti. oben P || ι O      10 Horiz. oben O: Ti. mittig P || ρ O: Ti. oben P || π ON      11 ο O: Ti. mittig P || α O: Ti. unten und dann oben P || ι O || ο O: Ti. (Rund.?) oben P || α,δ,λ || leicht gerund. Vert. (re. Teil von Buchst.) mit Verbi. mittig (υ wahrs.) || Vert. (Schräge) mit Verbi. oben (μ,ν wahrs.) || ϲ O: Rund. unten P || ε Ο: Ti. P || ϲ O: Ti. unten P || Ti. oben || Ti. oben (Teil von Horiz.?) O || ρ O || ε O: Ti. oben P || θ O      12 ο ON || υ O || Vert. || η,μ,ν O || λ Ο || ι O: Ti. mittig P      13 υ ON: Ti. P || Ti. || η̣ O: Ti. P || μ oder ν O: Ti. P || Ti. || ν̣,α̣ι,λ̣ι O || φυ O: Ti. mittig, Ti. mittig P      14 Ti. || ε O: Ti. P || ζ O: ζ oder ξ P: τ N || ι ON: Vert./´Schräge P || re. Fuß (α,δ,λ wahrs.) || α O: li. Teil von Dreieck unten || Ti. oben (re. Teil von Horiz. wahrs.)      15 λεγ O: Schräge, Ti. mittig, Ti. oben P || Ti. unten || Ti. unten || Fall. unten || θοιϲ O     16 λι O: Fall., Ti. mittig P || Rund. P: ι O || ϲτο O: Rund. unten, Vert., Rund. oben P || ϲ O: Ti. mittig P || τ̣ Ο: Vert. oben (mit Verbi.?) P      17 ο O: Ti. mittig P: ι N || Rund. mittig || Ti. unten/oben      18 ε Ο || ιϲτενκη O: Ti., Ti., Ti., Ti., Ti., Ti., Ti. P || Ti. unten || Vert. unten || Vert. || Vert. mit Verbi. (γ wahrs.) || Ti. unten || Ti. unten      19 ϲεπ̣ O || Ti. || Ti. || ο Ν: Ti. mittig P: ϲ N || υο ON: Schräge, Ti. unten P || υ̣ O: Ti. mittig P      20 νηγ O: Ti., Ti., Ti. P || π Ο: ν N: Ti. oben P || Ti. oben (Dreieck?) || Ti. mittig      21 Ti. || Ti. || Ti. || ν O: Schräge unten und Ti. mittig P || Ti. unten || Ti. unten (gleicher Buchst.?)      22 Rund. unten || Ti. unten (Fuß?) || Vert. und Ti. oben (π?) || ν O || Ti.       23 Horiz. unten || Ti. mittig || Vert. || Ti. unten || Ti. unten || Ti. mittig (ε?) || Schräge unten       24 Ti. oben || Ti. mittig || Ti. mittig || Ti. || Ti.       25  π oder τ || Ti. mittig || Dreieck mittig (δ oder ρ) || Horiz. oben || Ti. || το ON: ξ oder τ wahrs., Rund. P || Schräge und dann Fall. unten || κ O || α O: Ti. mittig P      26 Schräge || Ti. mittig || Ti. unten/oben (κ wahrs.) || α,δ,λ || Ti. unten || απαν O || η O: Ti. mittig P      27 Ti. || Ti. || Ti. unten || Rund. unten || Ti. mittig || ob. Teil von  Buchst. (α,δ,λ wahrs.) || Ti. unten || Ti. || Ti. oben O || διγω (Sovrapposto?) O || π oder τ   28 Ti. unten || Ti. unten || Ti. unten || Ti. oben || π oder τ || Fuß || Ti. mittig || Ti. unten || Ti. unten || ο Ο: Rund. (ο oder ω wahrs.) P || ιϲει O: Ti., Ti. mittig, Ti. mittig, Ti. mittig P || Rund.   29  Ti. oben    30 Schräge unten || Ti. oben || Ti. || Ti. oben || ζ Ο: Ti. P || li. Teil von Horiz. oben || re. Fuß unten      31 Schräge unten (α,δ,λ wahrs.) || Ti. (ε?) || Ti. (Schräge?) oben || Ti. oben || Ti. oben || Horiz. mittig || Ti. mittig || ε oder ϲ || Ti. unten/oben (ϲ wahrs.)      32 Ti. (Vert.?) mittig || Ti. || Ti. || Ti. (Rund.?) oben || Ti. mittig (Rund.?) || Rund. oben O: Ti. oben (Rund.?) P      33 Ti. || Ti. mittig || Ti. || Ti. (Vert.?) mittig/oben       34 Vert. || Ti. oben || Ti. oben || Fuß || Vert. || Ti. || Ti. || Ti. || Rund. unten || θ oder ϲ || π oder τ || ε,ο,ϲ || Ti. mittig (kleiner Buchst.)       35 Ti. || Ti. || Ti. oben || Rund. oben || Ti. || Ti. || Ti. || Ti. || ϲ O: Rund. P || φ O: Ti. P      36 Ti. unten || ϲ O: Ti. oben P || Rund. oben      37 ι O || β O: Ti. oben P      38 Vert. O || Ti. unten || υ O: Vert. unten P || ειϲ O: Ti., Ti., Rund. unten P      39 Vert. oben       40 Ti. mittig O || ι O: Vert. oben P || ω ON: Ti. oben und dann unten P || Fall. oben      42 ε O: Ti. unten P      44 Rund. oben || οϲ ON: Ti. unten/oben, Rund. oben P      45 η̣ O: Ti.      46 [Haken in O  - Horiz. und Teil von Vert. in P] ϲκ O: Ti., Ti. P || υ ON: Schräge unten P || Ti. 

</content>
        <language>gs-diplomatic-apparatus</language>
    </dsl>
</unit>