<?xml version="1.0" encoding="UTF-8"?>
<unit>
    <id>kol-v-pherc-1021-dip-app</id>
    <creator>Philodemus || Fleischer, Kilian J.</creator>
    <createdAt>1691590242641</createdAt>
    <title>Academicorum Index || Kol. V PHerc. 1021 || Diplomatic Apparatus</title>
    <target>kol-v-pherc-1021</target>
    <children/>
    <dsl>
        <content>

Auf den HSI finden sich einige unsichere Spuren von Buchst., wo das Disegno mehr Informationen gibt. In keinem Fall schließen diese Spuren die Lesung des Disegno aus Lediglich in Z. 4 könnte der Buchst. nach νο ein τ sein.  

3 τ oder υ || Vert. || Vert. oben und Schräge (κ wahrs.)     7  α oder λ || Ti. oben (Teil von Buchst.?)  11 Vert. 14 Ti. (Fall.?) || Horiz. oben   16 Fall.   17 ο oder ω || ο oder ω   18  Rund. || γ oder μ   19 Vert.  20 Vert. || Vert. mit kleiner Horiz. oben || Vert.

Viell. standen unter Z. 23 noch mehr Zeilen, aber das Disegno spricht nicht dafür.

</content>
        <language>gs-diplomatic-apparatus</language>
    </dsl>
</unit>