<?xml version="1.0" encoding="UTF-8"?>
<unit>
    <id>col-35-pherc-1004-lit-app</id>
    <creator>Philodemus || Ranocchia, Graziano et Vassallo, Christian</creator>
    <createdAt>1740254371727</createdAt>
    <title>De rhetorica || Col. 35 PHerc. 1004 || Literary Apparatus</title>
    <target>col-35-pherc-1004</target>
    <children/>
    <dsl>
        <content>Col. 35    primum edidimus        7 εὖ πρόϲ] (vel περί]) e.g. *        11 init. ἐγένεθ’] et fin. δ̣[υ]ϲ̣ί[ν e.g. *        12 κα]κ̣ῶϲ vel κα]λ̣ῶϲ et fin. [κα]τ̣’ e.g. *       16 λέγειν post δύ̣ναϲ̣|[θαι e.g. * 
</content>
        <language>gs-literary-apparatus</language>
    </dsl>
</unit>