<?xml version="1.0" encoding="UTF-8"?>
<unit>
    <id>col-75-pherc-1004-dip-tr</id>
    <creator>Philodemus || Ranocchia, Graziano et Vassallo, Christian</creator>
    <createdAt>1740682474889</createdAt>
    <title>De rhetorica || Col. 75 PHerc. 1004 || Diplomatic Transcription</title>
    <target>col-75-pherc-1004</target>
    <children/>
    <dsl>
        <content>desunt versus fere 24
  ̣  ̣  ̣  ̣  ̣  ̣  ̣]  ̣χ̣[  ̣  ̣   ̣]δ̣   ̣  ̣[  ̣  ̣
 ̣  ̣  ̣  ̣  ̣  ̣   ̣  ̣  ̣]εcθ̣α̣ιπρωι
 ̣  ̣  ̣  ̣  ̣  ̣  ̣]ε̣  ̣  ̣δεκαιπραττ̣ον̣
  ̣  ̣  ̣  ̣  ̣   ̣₍  ̣₎]  ̣[  ̣]  ̣ιcταευζη̣ν
  ̣   ̣  ̣  ̣  ̣  ̣  ̣  ̣]   ̣  ̣μ  ̣νχ  ̣ριεν
 ̣  ̣  ̣  ̣  ̣  ̣   ̣  ̣  ̣]  ̣ιν  ̣οcπερ̣
  ̣  ̣  ̣  ̣  ̣  ̣  ̣]  ̣  ̣[  ̣  ̣]  ̣  ̣  ̣φιλοcο
 ̣  ̣  ̣  ̣  ̣₍  ̣₎]  ̣ινου̣γαρανεποι
  ̣  ̣  ̣  ̣   ̣  ̣  ̣]  ̣[  ̣]υcειμηηναγα
  ̣  ̣  ̣  ̣  ̣]  ̣ ι̣α̣[  ̣]η  ̣ρητ̣ο̣
 ̣  ̣  ̣  ̣  ̣  ̣  ̣  ̣  ̣  ̣  ̣  ̣  ̣]α̣ιν̣  ̣νω
φ//[  ̣  ̣  ̣  ̣  ̣  ̣   ̣  ̣  ̣  ̣   ̣  ̣]  ̣τ̣ηκ̣αι̣
 ̣  ̣  ̣  ̣  ̣  ̣  ̣  ̣  ̣  ̣  ̣  ̣  ̣  ̣  ̣]α̣ιρ̣ε
  ̣  ̣  ̣  ̣  ̣  ̣   ̣  ̣  ̣  ̣  ̣  ̣  ̣]γαρδυ̣
  ̣  ̣  ̣  ̣  ̣   ̣   ̣  ̣  ̣  ̣  ̣  ̣  ̣  ̣  ̣]θ̣εινο
  ̣   ̣  ̣  ̣  ̣  ̣   ̣  ̣  ̣  ̣]θαι̣ρε  ̣ 
  ̣  ̣  ̣  ̣  ̣  ̣  ̣  ̣  ̣  ̣  ̣  ̣  ̣  ̣]ι̣κ̣αιτο
 ̣  ̣  ̣  ̣  ̣  ̣   ̣  ̣  ̣  ̣  ̣  ̣  ̣  ̣  ̣  ̣]ρ̣α[  ̣
 ̣  ̣  ̣  ̣  ̣  ̣  ̣  ̣  ̣  ̣  ̣  ̣  ̣  ̣]  ̣ξ̣ι  ̣[  ̣
deest versus unus

</content>
        <language>gs-diplomatic-transcription</language>
    </dsl>
</unit>